facedetectmodule.py
facemeshmodule.py
helloworld.py
mediapipeface-0.2.0.dist-info/LICENSE
mediapipeface-0.2.0.dist-info/METADATA
mediapipeface-0.2.0.dist-info/WHEEL
mediapipeface-0.2.0.dist-info/top_level.txt
mediapipeface-0.2.0.dist-info/RECORD
