Metadata-Version: 2.1
Name: mediapipeface
Version: 0.2.0
Summary: Mediapipe face implementations.
Home-page: https://github.com/Pritam-N/mediapipeface
Author: Pritama Nayak
Author-email: nayak264@gmail.com
License: UNKNOWN
Platform: UNKNOWN
Classifier: Programming Language :: Python :: 3
Classifier: Programming Language :: Python :: 3.7
Classifier: License :: OSI Approved :: MIT License
Classifier: Operating System :: OS Independent
Provides-Extra: dev
